wirepas_mesh_messaging/__about__.py
wirepas_mesh_messaging/__init__.py
wirepas_mesh_messaging/__main__.py
wirepas_mesh_messaging/config_helper.py
wirepas_mesh_messaging/event.py
wirepas_mesh_messaging/gateway_feature.py
wirepas_mesh_messaging/gateway_result_code.py
wirepas_mesh_messaging/get_config_data_item.py
wirepas_mesh_messaging/get_configs.py
wirepas_mesh_messaging/get_gw_info.py
wirepas_mesh_messaging/get_scratchpad_status.py
wirepas_mesh_messaging/otap_helper.py
wirepas_mesh_messaging/process_scratchpad.py
wirepas_mesh_messaging/received_data.py
wirepas_mesh_messaging/request.py
wirepas_mesh_messaging/response.py
wirepas_mesh_messaging/send_data.py
wirepas_mesh_messaging/set_config.py
wirepas_mesh_messaging/set_config_data_item.py
wirepas_mesh_messaging/set_scratchpad_target.py
wirepas_mesh_messaging/status.py
wirepas_mesh_messaging/upload_scratchpad.py
wirepas_mesh_messaging/wirepas_exceptions.py
wirepas_mesh_messaging/wirepas_message.py
wirepas_mesh_messaging/proto/__init__.py
wirepas_mesh_messaging/proto/config_message_pb2.py
wirepas_mesh_messaging/proto/data_message_pb2.py
wirepas_mesh_messaging/proto/error_pb2.py
wirepas_mesh_messaging/proto/generic_message_pb2.py
wirepas_mesh_messaging/proto/otap_message_pb2.py
wirepas_mesh_messaging/proto/wp_global_pb2.py
wirepas_mesh_messaging-1.3.0.dist-info/licenses/LICENSE
wirepas_mesh_messaging-1.3.0.dist-info/METADATA
wirepas_mesh_messaging-1.3.0.dist-info/WHEEL
wirepas_mesh_messaging-1.3.0.dist-info/top_level.txt
wirepas_mesh_messaging-1.3.0.dist-info/RECORD
