Metadata-Version: 2.4
Name: wirepas_mesh_messaging
Version: 1.3.0
Summary: Wrapper interfaces to interact with Backend to/from Gateway API.
Home-page: https://github.com/wirepas/backend-apis/tree/master/gateway_to_backend
Author: Wirepas Ltd
Author-email: opensource@wirepas.com
License: Apache-2
Keywords: wirepas connectivity iot mesh gateway backend
Classifier: Development Status :: 5 - Production/Stable
Classifier: Intended Audience :: Developers
Classifier: License :: OSI Approved :: Apache Software License
Classifier: Topic :: Software Development :: Libraries
Classifier: Programming Language :: Python :: 3
License-File: LICENSE
Requires-Dist: protobuf~=6.31.1
Dynamic: author
Dynamic: author-email
Dynamic: classifier
Dynamic: description
Dynamic: description-content-type
Dynamic: home-page
Dynamic: keywords
Dynamic: license
Dynamic: license-file
Dynamic: requires-dist
Dynamic: summary
